[
  {
    "$kitaptaki_turkce": "alçalmak",
    "lehce_id": "128",
    "asil": "alçalmak",
    "turkce": "alçalmak",
    "azerice1": "alçalmag",
    "azerice2": null,
    "azerice3": null,
    "azerice4": null,
    "baskurtca1": "tübängä (aska) töşöv",
    "baskurtca2": null,
    "baskurtca3": null,
    "baskurtca4": null,
    "kazakca1": "tömendev",
    "kazakca2": "ıldıylav",
    "kazakca3": null,
    "kazakca4": null,
    "kirgizca1": "tömöndȫ",
    "kirgizca2": "ıldıylō",
    "kirgizca3": null,
    "kirgizca4": null,
    "ozbekce1": "pästlämàk",
    "ozbekce2": "päsäymàk",
    "ozbekce3": null,
    "ozbekce4": null,
    "tatarca1": "tübängä (aska) töşü",
    "tatarca2": null,
    "tatarca3": null,
    "tatarca4": null,
    "turkmence1": "peselmek",
    "turkmence2": "aşãklamak",
    "turkmence3": null,
    "turkmence4": null,
    "uygurca1": "tòvänlimäk",
    "uygurca2": "päslimäk",
    "uygurca3": null,
    "uygurca4": null,
    "rusca1": "ponijat's'a",
    "rusca2": null,
    "rusca3": null,
    "rusca4": null
  }
]