[
  {
    "$kitaptaki_turkce": "ayı",
    "lehce_id": "294",
    "asil": "ayı",
    "turkce": "ayı",
    "azerice1": "ayı",
    "azerice2": null,
    "azerice3": null,
    "azerice4": null,
    "baskurtca1": "ayıv",
    "baskurtca2": null,
    "baskurtca3": null,
    "baskurtca4": null,
    "kazakca1": "ayuv",
    "kazakca2": null,
    "kazakca3": null,
    "kazakca4": null,
    "kirgizca1": "ayū",
    "kirgizca2": null,
    "kirgizca3": null,
    "kirgizca4": null,
    "ozbekce1": "äyık",
    "ozbekce2": null,
    "ozbekce3": null,
    "ozbekce4": null,
    "tatarca1": "ayu",
    "tatarca2": null,
    "tatarca3": null,
    "tatarca4": null,
    "turkmence1": "ayı",
    "turkmence2": null,
    "turkmence3": null,
    "turkmence4": null,
    "uygurca1": "eyiḳ",
    "uygurca2": null,
    "uygurca3": null,
    "uygurca4": null,
    "rusca1": "med'ved'",
    "rusca2": null,
    "rusca3": null,
    "rusca4": null
  }
]