[
  {
    "$kitaptaki_turkce": "başarmak",
    "lehce_id": "406",
    "asil": "başarmak",
    "turkce": "başarmak",
    "azerice1": "müväffäģ olmag",
    "azerice2": null,
    "azerice3": null,
    "azerice4": null,
    "baskurtca1": "bötöröv",
    "baskurtca2": " tamamlav",
    "baskurtca3": " tivälläv (uŋışlı)",
    "baskurtca4": null,
    "kazakca1": "iske asıruv",
    "kazakca2": null,
    "kazakca3": null,
    "kazakca4": null,
    "kirgizca1": "bütṻ",
    "kirgizca2": "atkarū",
    "kirgizca3": null,
    "kirgizca4": null,
    "ozbekce1": "tügätmàḳ (muvaffaḳiyät bilän)",
    "ozbekce2": "muvaffaḳ bolmàḳ",
    "ozbekce3": null,
    "ozbekce4": null,
    "tatarca1": "bitirü",
    "tatarca2": "tamamlau",
    "tatarca3": "tögälläv (uŋışlı)",
    "tatarca4": null,
    "turkmence1": "başarmak",
    "turkmence2": null,
    "turkmence3": null,
    "turkmence4": null,
    "uygurca1": "utukka egä bolmak",
    "uygurca2": "muväppäḳiyät kazanmak",
    "uygurca3": null,
    "uygurca4": null,
    "rusca1": "zaverş'at'",
    "rusca2": "konçat'",
    "rusca3": "vipóln'at ",
    "rusca4": null
  }
]