[
  {
    "$kitaptaki_turkce": "bedāva",
    "lehce_id": "439",
    "asil": "bedava",
    "turkce": "bedava",
    "azerice1": "pulsuz",
    "azerice2": "havãyı",
    "azerice3": "müftä",
    "azerice4": null,
    "baskurtca1": "tülävhiⱬ",
    "baskurtca2": "buş",
    "baskurtca3": "aksahıⱬ",
    "baskurtca4": "ⱨakhⱬ",
    "kazakca1": "tegin",
    "kazakca2": null,
    "kazakca3": null,
    "kazakca4": null,
    "kirgizca1": "beker ",
    "kirgizca2": "akçasiz",
    "kirgizca3": null,
    "kirgizca4": null,
    "ozbekce1": "tekin",
    "ozbekce2": null,
    "ozbekce3": null,
    "ozbekce4": null,
    "tatarca1": "tülävsiz",
    "tatarca2": "buş",
    "tatarca3": "akçasız",
    "tatarca4": "ⱨaksız",
    "turkmence1": "muğt",
    "turkmence2": "pulsuz",
    "turkmence3": null,
    "turkmence4": null,
    "uygurca1": "pulsiz",
    "uygurca2": "tekin",
    "uygurca3": "bikar",
    "uygurca4": null,
    "rusca1": "besplatnıy",
    "rusca2": "darovóy",
    "rusca3": null,
    "rusca4": null
  }
]