[
  {
    "$kitaptaki_turkce": "beynamaz",
    "lehce_id": "490",
    "asil": "beynamaz",
    "turkce": "beynamaz",
    "azerice1": "beynamaz",
    "azerice2": null,
    "azerice3": null,
    "azerice4": null,
    "baskurtca1": "namaⱬ ukımay torğan kişi",
    "baskurtca2": null,
    "baskurtca3": null,
    "baskurtca4": null,
    "kazakca1": "beynamaz",
    "kazakca2": null,
    "kazakca3": null,
    "kazakca4": null,
    "kirgizca1": "beynamaz",
    "kirgizca2": null,
    "kirgizca3": null,
    "kirgizca4": null,
    "ozbekce1": "benämàz",
    "ozbekce2": null,
    "ozbekce3": null,
    "ozbekce4": null,
    "tatarca1": "namaz ukımıy",
    "tatarca2": "torğan kişi",
    "tatarca3": null,
    "tatarca4": null,
    "turkmence1": "bḯnamãz",
    "turkmence2": "namãzsız",
    "turkmence3": null,
    "turkmence4": null,
    "uygurca1": "bḯnamaz",
    "uygurca2": null,
    "uygurca3": null,
    "uygurca4": null,
    "rusca1": "(çelovek) ne",
    "rusca2": "soverşayuşçiy",
    "rusca3": "namaz",
    "rusca4": null
  }
]