[
  {
    "$kitaptaki_turkce": "birikmek",
    "lehce_id": "541",
    "asil": "birikmek",
    "turkce": "birikmek",
    "azerice1": "birikmäk",
    "azerice2": "yığıltmag",
    "azerice3": null,
    "azerice4": null,
    "baskurtca1": "yıyılıv",
    "baskurtca2": "tuplanıv",
    "baskurtca3": "yıynav",
    "baskurtca4": null,
    "kazakca1": "jıynaluv",
    "kazakca2": "jıyıluv",
    "kazakca3": null,
    "kazakca4": null,
    "kirgizca1": "kosulū",
    "kirgizca2": "cıyılū",
    "kirgizca3": "birigṻ ",
    "kirgizca4": null,
    "ozbekce1": "toplänmàḳ",
    "ozbekce2": "yiğılmàḳ",
    "ozbekce3": null,
    "ozbekce4": null,
    "tatarca1": "cıyılu",
    "tatarca2": "tuptanu",
    "tatarca3": "cıynau",
    "tatarca4": null,
    "turkmence1": "toplanmak",
    "turkmence2": "yığnanmak",
    "turkmence3": null,
    "turkmence4": null,
    "uygurca1": "birikmäk",
    "uygurca2": "jiğilmak",
    "uygurca3": null,
    "uygurca4": null,
    "rusca1": "skaplivat's'a",
    "rusca2": "nakaplivat's'a",
    "rusca3": "sobirat's'a",
    "rusca4": null
  }
]