[
  {
    "$kitaptaki_turkce": "dantel",
    "lehce_id": "1064",
    "asil": "dantel",
    "turkce": "dantel",
    "azerice1": "hörmä",
    "azerice2": "naⱨış",
    "azerice3": null,
    "azerice4": null,
    "baskurtca1": "siltär",
    "baskurtca2": null,
    "baskurtca3": null,
    "baskurtca4": null,
    "kazakca1": "tor",
    "kazakca2": "tor köz",
    "kazakca3": null,
    "kazakca4": null,
    "kirgizca1": "tor keşte",
    "kirgizca2": "keşte çaçısı",
    "kirgizca3": null,
    "kirgizca4": null,
    "ozbekce1": "tor käştä",
    "ozbekce2": null,
    "ozbekce3": null,
    "ozbekce4": null,
    "tatarca1": "çiltär",
    "tatarca2": null,
    "tatarca3": null,
    "tatarca4": null,
    "turkmence1": "tor nağış",
    "turkmence2": null,
    "turkmence3": null,
    "turkmence4": null,
    "uygurca1": "tor käştä",
    "uygurca2": null,
    "uygurca3": null,
    "uygurca4": null,
    "rusca1": "krujevo",
    "rusca2": null,
    "rusca3": null,
    "rusca4": null
  }
]