[
  {
    "$kitaptaki_turkce": "devirmek",
    "lehce_id": "1211",
    "asil": "devirmek",
    "turkce": "devirmek",
    "azerice1": "devirmäk",
    "azerice2": null,
    "azerice3": null,
    "azerice4": null,
    "baskurtca1": "avⱬarıv",
    "baskurtca2": "tüŋkäriv",
    "baskurtca3": "kolatıv",
    "baskurtca4": null,
    "kazakca1": "kulatıv",
    "kazakca2": "jıģuv",
    "kazakca3": "töŋḳerüv",
    "kazakca4": null,
    "kirgizca1": "kulatū",
    "kirgizca2": "cığū",
    "kirgizca3": null,
    "kirgizca4": null,
    "ozbekce1": "ağdärmàḳ",
    "ozbekce2": "ḳulätmàḳ",
    "ozbekce3": null,
    "ozbekce4": null,
    "tatarca1": "tüntärü",
    "tatarca2": "avdaru",
    "tatarca3": null,
    "tatarca4": null,
    "turkmence1": "yıkmak",
    "turkmence2": "ãğdarmak",
    "turkmence3": null,
    "turkmence4": null,
    "uygurca1": "ağdurmak",
    "uygurca2": "ğulatmak",
    "uygurca3": null,
    "uygurca4": null,
    "rusca1": "valit'",
    "rusca2": "oprokidıvat'",
    "rusca3": "perevortıvat'",
    "rusca4": null
  }
]