[
  {
    "$kitaptaki_turkce": "değer",
    "lehce_id": "1101",
    "asil": "değer",
    "turkce": "değer",
    "azerice1": "däyär",
    "azerice2": "ģiymät",
    "azerice3": null,
    "azerice4": null,
    "baskurtca1": "ḳimmät",
    "baskurtca2": "baha",
    "baskurtca3": null,
    "baskurtca4": null,
    "kazakca1": "bağa",
    "kazakca2": "kundılık",
    "kazakca3": null,
    "kazakca4": null,
    "kirgizca1": "bã",
    "kirgizca2": "nark",
    "kirgizca3": null,
    "kirgizca4": null,
    "ozbekce1": "bähà",
    "ozbekce2": "ḳıymät",
    "ozbekce3": null,
    "ozbekce4": null,
    "tatarca1": "kıymmät",
    "tatarca2": "bäyä",
    "tatarca3": null,
    "tatarca4": null,
    "turkmence1": "baha",
    "turkmence2": "nırh",
    "turkmence3": "gīmmat",
    "turkmence4": null,
    "uygurca1": "baha",
    "uygurca2": "ḳimmät",
    "uygurca3": "närⱨ",
    "uygurca4": null,
    "rusca1": "tsena",
    "rusca2": "stóimost'",
    "rusca3": null,
    "rusca4": null
  }
]