[
  {
    "$kitaptaki_turkce": "dönek",
    "lehce_id": "1348",
    "asil": "dönek",
    "turkce": "dönek",
    "azerice1": "dönäk",
    "azerice2": null,
    "azerice3": null,
    "azerice4": null,
    "baskurtca1": "üⱬgärivsän",
    "baskurtca2": "almaşınıvsan",
    "baskurtca3": null,
    "baskurtca4": null,
    "kazakca1": "suvkıyt",
    "kazakca2": "suvayt",
    "kazakca3": null,
    "kazakca4": null,
    "kirgizca1": "sözünö turbağan",
    "kirgizca2": "kaypak",
    "kirgizca3": null,
    "kirgizca4": null,
    "ozbekce1": "betäyin",
    "ozbekce2": "tuturıḳsiz",
    "ozbekce3": "özgäruvçän",
    "ozbekce4": null,
    "tatarca1": "üzgärüçän",
    "tatarca2": "almaşınuçan",
    "tatarca3": null,
    "tatarca4": null,
    "turkmence1": "durnuksız",
    "turkmence2": "ırğa",
    "turkmence3": null,
    "turkmence4": null,
    "uygurca1": "tutruksiz",
    "uygurca2": "bivapa",
    "uygurca3": null,
    "uygurca4": null,
    "rusca1": "nepostoyannıy",
    "rusca2": "peremençivıy",
    "rusca3": null,
    "rusca4": null
  }
]