[
  {
    "$kitaptaki_turkce": "dürüst",
    "lehce_id": "1411",
    "asil": "dürüst",
    "turkce": "dürüst",
    "azerice1": "dürüst",
    "azerice2": null,
    "azerice3": null,
    "azerice4": null,
    "baskurtca1": "ğäⱬil",
    "baskurtca2": "toğro",
    "baskurtca3": "ısın",
    "baskurtca4": null,
    "kazakca1": "şınşıl",
    "kazakca2": null,
    "kazakca3": null,
    "kazakca4": null,
    "kirgizca1": "çınçıl",
    "kirgizca2": "tūra",
    "kirgizca3": null,
    "kirgizca4": null,
    "ozbekce1": "ràstgöy",
    "ozbekce2": "häḳıḳatçi",
    "ozbekce3": "toğri",
    "ozbekce4": null,
    "tatarca1": "ğadil",
    "tatarca2": "turı",
    "tatarca3": "çın",
    "tatarca4": null,
    "turkmence1": "doğruçıl",
    "turkmence2": "hakıkatçıl",
    "turkmence3": null,
    "turkmence4": null,
    "uygurca1": "rastçi",
    "uygurca2": "häḳiḳätçi",
    "uygurca3": null,
    "uygurca4": null,
    "rusca1": "pravdivıy",
    "rusca2": null,
    "rusca3": null,
    "rusca4": null
  }
]