[
  {
    "$kitaptaki_turkce": "farazā",
    "lehce_id": "1698",
    "asil": "faraza",
    "turkce": "faraza",
    "azerice1": "tutag ki",
    "azerice2": null,
    "azerice3": null,
    "azerice4": null,
    "baskurtca1": "faraⱬ itäyik",
    "baskurtca2": null,
    "baskurtca3": null,
    "baskurtca4": null,
    "kazakca1": "eger",
    "kazakca2": "aytalık",
    "kazakca3": "nemese",
    "kazakca4": null,
    "kirgizca1": "eger ",
    "kirgizca2": "egerde",
    "kirgizca3": null,
    "kirgizca4": null,
    "ozbekce1": "äytäylik ",
    "ozbekce2": "färäz ḳıläylik",
    "ozbekce3": null,
    "ozbekce4": null,
    "tatarca1": "faraz itik",
    "tatarca2": null,
    "tatarca3": null,
    "tatarca4": null,
    "turkmence1": "diyeli",
    "turkmence2": null,
    "turkmence3": null,
    "turkmence4": null,
    "uygurca1": "päräzan ",
    "uygurca2": "bolsunki",
    "uygurca3": null,
    "uygurca4": null,
    "rusca1": "predpolójim ",
    "rusca2": "çto ",
    "rusca3": "dopustim",
    "rusca4": null
  }
]