[
  {
    "$kitaptaki_turkce": "hāricī",
    "lehce_id": "2228",
    "asil": "harici",
    "turkce": "harici",
    "azerice1": "ⱨarici",
    "azerice2": null,
    "azerice3": null,
    "azerice4": null,
    "baskurtca1": "tış(kı)",
    "baskurtca2": null,
    "baskurtca3": null,
    "baskurtca4": null,
    "kazakca1": "tıs(kı)",
    "kazakca2": "sırt(kı)",
    "kazakca3": null,
    "kazakca4": null,
    "kirgizca1": "tışkı",
    "kirgizca2": "sırtkı",
    "kirgizca3": null,
    "kirgizca4": null,
    "ozbekce1": "ⱨàriciy",
    "ozbekce2": "taşkı",
    "ozbekce3": null,
    "ozbekce4": null,
    "tatarca1": "tış(kı)",
    "tatarca2": null,
    "tatarca3": null,
    "tatarca4": null,
    "turkmence1": "daşkı",
    "turkmence2": "taşḳı",
    "turkmence3": null,
    "turkmence4": null,
    "uygurca1": "taşkı",
    "uygurca2": "çätki",
    "uygurca3": null,
    "uygurca4": null,
    "rusca1": "vneşniy",
    "rusca2": "narujniy",
    "rusca3": null,
    "rusca4": null
  }
]