[
  {
    "$kitaptaki_turkce": "hasta",
    "lehce_id": "2257",
    "asil": "hasta",
    "turkce": "hasta",
    "azerice1": "ⱨästä",
    "azerice2": null,
    "azerice3": null,
    "azerice4": null,
    "baskurtca1": "ⱨasta",
    "baskurtca2": "avırıv",
    "baskurtca3": "sırⱨav",
    "baskurtca4": null,
    "kazakca1": "avruv",
    "kazakca2": "navkas",
    "kazakca3": "dert",
    "kazakca4": null,
    "kirgizca1": "ōrū",
    "kirgizca2": "kesel",
    "kirgizca3": null,
    "kirgizca4": null,
    "ozbekce1": "käsäl",
    "ozbekce2": "ⱨastä",
    "ozbekce3": null,
    "ozbekce4": null,
    "tatarca1": "ⱨästä",
    "tatarca2": "avınv",
    "tatarca3": "sırⱨav",
    "tatarca4": null,
    "turkmence1": "hassa",
    "turkmence2": "sırkav",
    "turkmence3": null,
    "turkmence4": null,
    "uygurca1": "hasta",
    "uygurca2": "kesäl",
    "uygurca3": null,
    "uygurca4": null,
    "rusca1": "bol'noy",
    "rusca2": null,
    "rusca3": null,
    "rusca4": null
  }
]