[
  {
    "$kitaptaki_turkce": "hınç",
    "lehce_id": "2390",
    "asil": "hınç",
    "turkce": "hınç",
    "azerice1": "hirs",
    "azerice2": "kin",
    "azerice3": "ģäzäb",
    "azerice4": null,
    "baskurtca1": "kürä almavsılık",
    "baskurtca2": "näfrät",
    "baskurtca3": null,
    "baskurtca4": null,
    "kazakca1": "öşpendilik",
    "kazakca2": null,
    "kazakca3": null,
    "kazakca4": null,
    "kirgizca1": "kektȫ",
    "kirgizca2": null,
    "kirgizca3": null,
    "kirgizca4": null,
    "ozbekce1": "ginä-küdürät",
    "ozbekce2": "näfrät",
    "ozbekce3": "kek",
    "ozbekce4": null,
    "tatarca1": "näfrät",
    "tatarca2": "küralmav",
    "tatarca3": null,
    "tatarca4": null,
    "turkmence1": "ȫç",
    "turkmence2": "gahar-gazap",
    "turkmence3": null,
    "turkmence4": null,
    "uygurca1": "öcmänlik",
    "uygurca2": "näprät",
    "uygurca3": null,
    "uygurca4": null,
    "rusca1": "nenavist'",
    "rusca2": "zlóba",
    "rusca3": "jajda mesti",
    "rusca4": null
  }
]