[
  {
    "$kitaptaki_turkce": "indirim",
    "lehce_id": "2758",
    "asil": "indirim",
    "turkce": "indirim",
    "azerice1": "ucuzlaşdırma",
    "azerice2": "endirmä",
    "azerice3": null,
    "azerice4": null,
    "baskurtca1": "oshoⱬlatıv",
    "baskurtca2": "kämitiv",
    "baskurtca3": "töşöröv",
    "baskurtca4": null,
    "kazakca1": "tüsirüv",
    "kazakca2": "arzandatuv",
    "kazakca3": "tömendetüv",
    "kazakca4": null,
    "kirgizca1": "arzandatū",
    "kirgizca2": null,
    "kirgizca3": null,
    "kirgizca4": null,
    "ozbekce1": "bähàsini tüşiriş",
    "ozbekce2": "ärzànläştiriş",
    "ozbekce3": null,
    "ozbekce4": null,
    "tatarca1": "oçsızlatu",
    "tatarca2": "kämitü",
    "tatarca3": "tösirü",
    "tatarca4": null,
    "turkmence1": "arzãnlatma",
    "turkmence2": "bahãsını aşãklatma",
    "turkmence3": null,
    "turkmence4": null,
    "uygurca1": "baha çüşürüş",
    "uygurca2": "ärzänlitiş",
    "uygurca3": null,
    "uygurca4": null,
    "rusca1": "snijeniye",
    "rusca2": "skidka",
    "rusca3": null,
    "rusca4": null
  }
]