[
  {
    "$kitaptaki_turkce": "insan",
    "lehce_id": "2772",
    "asil": "insan",
    "turkce": "insan",
    "azerice1": "insan",
    "azerice2": null,
    "azerice3": null,
    "azerice4": null,
    "baskurtca1": "insan",
    "baskurtca2": "kişi",
    "baskurtca3": "ädäm",
    "baskurtca4": null,
    "kazakca1": "adam",
    "kazakca2": "kişi",
    "kazakca3": null,
    "kazakca4": null,
    "kirgizca1": "adam",
    "kirgizca2": "kişi",
    "kirgizca3": null,
    "kirgizca4": null,
    "ozbekce1": "insàn",
    "ozbekce2": "àdäm",
    "ozbekce3": null,
    "ozbekce4": null,
    "tatarca1": "insan",
    "tatarca2": "kişi",
    "tatarca3": "adäm",
    "tatarca4": null,
    "turkmence1": "ınsãn",
    "turkmence2": "ãdam",
    "turkmence3": null,
    "turkmence4": null,
    "uygurca1": "insan",
    "uygurca2": null,
    "uygurca3": null,
    "uygurca4": null,
    "rusca1": "çelovek",
    "rusca2": null,
    "rusca3": null,
    "rusca4": null
  }
]