[
  {
    "$kitaptaki_turkce": "kadın",
    "lehce_id": "2938",
    "asil": "kadın",
    "turkce": "kadın",
    "azerice1": "gadın",
    "azerice2": null,
    "azerice3": null,
    "azerice4": null,
    "baskurtca1": "katın",
    "baskurtca2": null,
    "baskurtca3": null,
    "baskurtca4": null,
    "kazakca1": "äyel",
    "kazakca2": null,
    "kazakca3": null,
    "kazakca4": null,
    "kirgizca1": "katın",
    "kirgizca2": "ayal",
    "kirgizca3": null,
    "kirgizca4": null,
    "ozbekce1": "ⱨatin",
    "ozbekce2": "äyàl",
    "ozbekce3": null,
    "ozbekce4": null,
    "tatarca1": "ⱨatın",
    "tatarca2": null,
    "tatarca3": null,
    "tatarca4": null,
    "turkmence1": "ayãl",
    "turkmence2": "hãtın",
    "turkmence3": null,
    "turkmence4": null,
    "uygurca1": "ayal",
    "uygurca2": "ⱨotun",
    "uygurca3": null,
    "uygurca4": null,
    "rusca1": "jenşçina",
    "rusca2": null,
    "rusca3": null,
    "rusca4": null
  }
]