[
  {
    "$kitaptaki_turkce": "kanepe",
    "lehce_id": "3022",
    "asil": "kanepe",
    "turkce": "kanepe",
    "azerice1": "divan",
    "azerice2": null,
    "azerice3": null,
    "azerice4": null,
    "baskurtca1": "känäfi",
    "baskurtca2": null,
    "baskurtca3": null,
    "baskurtca4": null,
    "kazakca1": "diyvan",
    "kazakca2": null,
    "kazakca3": null,
    "kazakca4": null,
    "kirgizca1": "divan",
    "kirgizca2": null,
    "kirgizca3": null,
    "kirgizca4": null,
    "ozbekce1": "divan",
    "ozbekce2": null,
    "ozbekce3": null,
    "ozbekce4": null,
    "tatarca1": "känäfi",
    "tatarca2": null,
    "tatarca3": null,
    "tatarca4": null,
    "turkmence1": "dḯvãn",
    "turkmence2": null,
    "turkmence3": null,
    "turkmence4": null,
    "uygurca1": "divan",
    "uygurca2": null,
    "uygurca3": null,
    "uygurca4": null,
    "rusca1": "divan",
    "rusca2": null,
    "rusca3": null,
    "rusca4": null
  }
]