[
  {
    "$kitaptaki_turkce": "kestirme",
    "lehce_id": "3328",
    "asil": "kestirme",
    "turkce": "kestirme",
    "azerice1": "käsä",
    "azerice2": null,
    "azerice3": null,
    "azerice4": null,
    "baskurtca1": "kıska yul",
    "baskurtca2": null,
    "baskurtca3": null,
    "baskurtca4": null,
    "kazakca1": "kıska",
    "kazakca2": "eŋ kıska",
    "kazakca3": null,
    "kazakca4": null,
    "kirgizca1": "kıska",
    "kirgizca2": "kıskaça",
    "kirgizca3": null,
    "kirgizca4": null,
    "ozbekce1": "kıska (yol)",
    "ozbekce2": null,
    "ozbekce3": null,
    "ozbekce4": null,
    "tatarca1": "kıska yul",
    "tatarca2": null,
    "tatarca3": null,
    "tatarca4": null,
    "turkmence1": "gīsğa yōl",
    "turkmence2": null,
    "turkmence3": null,
    "turkmence4": null,
    "uygurca1": "kıska yol",
    "uygurca2": null,
    "uygurca3": null,
    "uygurca4": null,
    "rusca1": "kratkiy",
    "rusca2": "kratçayşiy",
    "rusca3": null,
    "rusca4": null
  }
]