{
  "$kitaptaki_turkce": "kokuşmak (tefessüh)",
  "asil": "kokuşmak (tefessüh)",
  "lehce_id": "3489",
  "turkce": "kokuşmak",
  "azerice1": "cürümäk",
  "azerice2": "goⱨulaşmag",
  "azerice3": null,
  "azerice4": null,
  "baskurtca1": "siriv",
  "baskurtca2": "tarkalıv",
  "baskurtca3": null,
  "baskurtca4": null,
  "kazakca1": "bülinüv",
  "kazakca2": null,
  "kazakca3": null,
  "kazakca4": null,
  "kirgizca1": "buzulū",
  "kirgizca2": "bülünṻ",
  "kirgizca3": null,
  "kirgizca4": null,
  "ozbekce1": "çirimàk",
  "ozbekce2": null,
  "ozbekce3": null,
  "ozbekce4": null,
  "tatarca1": "çirü",
  "tatarca2": "tarkalu",
  "tatarca3": null,
  "tatarca4": null,
  "turkmence1": "çṻyremek",
  "turkmence2": "bozulmak",
  "turkmence3": null,
  "turkmence4": null,
  "uygurca1": "çirimäk",
  "uygurca2": "buzulmak",
  "uygurca3": null,
  "uygurca4": null,
  "rusca1": "razlojit's'a",
  "rusca2": null,
  "rusca3": null,
  "rusca4": null
}