[
  {
    "$kitaptaki_turkce": "kulak",
    "lehce_id": "3646",
    "asil": "kulak",
    "turkce": "kulak",
    "azerice1": "gulag",
    "azerice2": null,
    "azerice3": null,
    "azerice4": null,
    "baskurtca1": "kolak",
    "baskurtca2": null,
    "baskurtca3": null,
    "baskurtca4": null,
    "kazakca1": "kulak",
    "kazakca2": null,
    "kazakca3": null,
    "kazakca4": null,
    "kirgizca1": "kulak",
    "kirgizca2": null,
    "kirgizca3": null,
    "kirgizca4": null,
    "ozbekce1": "kulàk",
    "ozbekce2": null,
    "ozbekce3": null,
    "ozbekce4": null,
    "tatarca1": "kolak",
    "tatarca2": null,
    "tatarca3": null,
    "tatarca4": null,
    "turkmence1": "gulak",
    "turkmence2": null,
    "turkmence3": null,
    "turkmence4": null,
    "uygurca1": "kulak",
    "uygurca2": null,
    "uygurca3": null,
    "uygurca4": null,
    "rusca1": "uⱨo",
    "rusca2": null,
    "rusca3": null,
    "rusca4": null
  }
]