[
  {
    "$kitaptaki_turkce": "lâpa",
    "lehce_id": "3817",
    "asil": "lâpa",
    "turkce": "lapa",
    "azerice1": "şilä",
    "azerice2": null,
    "azerice3": null,
    "azerice4": null,
    "baskurtca1": "butka",
    "baskurtca2": null,
    "baskurtca3": null,
    "baskurtca4": null,
    "kazakca1": "botka",
    "kazakca2": null,
    "kazakca3": null,
    "kazakca4": null,
    "kirgizca1": "kürüç botko",
    "kirgizca2": null,
    "kirgizca3": null,
    "kirgizca4": null,
    "ozbekce1": "botka",
    "ozbekce2": null,
    "ozbekce3": null,
    "ozbekce4": null,
    "tatarca1": "botka",
    "tatarca2": null,
    "tatarca3": null,
    "tatarca4": null,
    "turkmence1": "şüle",
    "turkmence2": null,
    "turkmence3": null,
    "turkmence4": null,
    "uygurca1": "şilvä",
    "uygurca2": "şola",
    "uygurca3": null,
    "uygurca4": null,
    "rusca1": "kaşa",
    "rusca2": null,
    "rusca3": null,
    "rusca4": null
  }
]