[
  {
    "$kitaptaki_turkce": "lüks",
    "lehce_id": "3877",
    "asil": "lüks",
    "turkce": "lüks",
    "azerice1": "lüks",
    "azerice2": null,
    "azerice3": null,
    "azerice4": null,
    "baskurtca1": "lüks",
    "baskurtca2": null,
    "baskurtca3": null,
    "baskurtca4": null,
    "kazakca1": "askan jaksı (lık)",
    "kazakca2": null,
    "kazakca3": null,
    "kazakca4": null,
    "kirgizca1": "(cakşı) ıŋğay",
    "kirgizca2": "(cakşı) şart",
    "kirgizca3": null,
    "kirgizca4": null,
    "ozbekce1": "lüks",
    "ozbekce2": null,
    "ozbekce3": null,
    "ozbekce4": null,
    "tatarca1": "lüks",
    "tatarca2": null,
    "tatarca3": null,
    "tatarca4": null,
    "turkmence1": "lyuks",
    "turkmence2": "rãhatlık",
    "turkmence3": null,
    "turkmence4": null,
    "uygurca1": "lüks",
    "uygurca2": null,
    "uygurca3": null,
    "uygurca4": null,
    "rusca1": "roskoş'",
    "rusca2": "lüks",
    "rusca3": null,
    "rusca4": null
  }
]