[
  {
    "$kitaptaki_turkce": "mefrūşat",
    "lehce_id": "4078",
    "asil": "mefruşat",
    "turkce": "mefruşat",
    "azerice1": "mebel äşyaları",
    "azerice2": null,
    "azerice3": null,
    "azerice4": null,
    "baskurtca1": "yıhaz",
    "baskurtca2": "mebel'",
    "baskurtca3": null,
    "baskurtca4": null,
    "kazakca1": "jiyhaz",
    "kazakca2": null,
    "kazakca3": null,
    "kazakca4": null,
    "kirgizca1": "emerek",
    "kirgizca2": null,
    "kirgizca3": null,
    "kirgizca4": null,
    "ozbekce1": "cihàz",
    "ozbekce2": "üy cihàzi",
    "ozbekce3": null,
    "ozbekce4": null,
    "tatarca1": "cihaz",
    "tatarca2": "mebel'",
    "tatarca3": null,
    "tatarca4": null,
    "turkmence1": "mebel",
    "turkmence2": null,
    "turkmence3": null,
    "turkmence4": null,
    "uygurca1": "cihaz",
    "uygurca2": "öy cihazliri",
    "uygurca3": null,
    "uygurca4": null,
    "rusca1": "ubranstvo",
    "rusca2": "mebel'",
    "rusca3": "obstanovka",
    "rusca4": null
  }
]