[
  {
    "$kitaptaki_turkce": "müfreze",
    "lehce_id": "4406",
    "asil": "müfreze",
    "turkce": "müfreze",
    "azerice1": "härbi dästä",
    "azerice2": null,
    "azerice3": null,
    "azerice4": null,
    "baskurtca1": "bülik ",
    "baskurtca2": "otdeleniye",
    "baskurtca3": null,
    "baskurtca4": null,
    "kazakca1": "äskeriy top",
    "kazakca2": null,
    "kazakca3": null,
    "kazakca4": null,
    "kirgizca1": "asker tobu",
    "kirgizca2": null,
    "kirgizca3": null,
    "kirgizca4": null,
    "ozbekce1": "äskäriy kısm",
    "ozbekce2": null,
    "ozbekce3": null,
    "ozbekce4": null,
    "tatarca1": "bülik ",
    "tatarca2": "otdeleniye",
    "tatarca3": null,
    "tatarca4": null,
    "turkmence1": "bȫlüm ",
    "turkmence2": "komanda",
    "turkmence3": null,
    "turkmence4": null,
    "uygurca1": "ⱨärbiy kısım",
    "uygurca2": null,
    "uygurca3": null,
    "uygurca4": null,
    "rusca1": "otr'ad",
    "rusca2": "komanda",
    "rusca3": null,
    "rusca4": null
  }
]