[
  {
    "$kitaptaki_turkce": "müstensih",
    "lehce_id": "4485",
    "asil": "müstensih",
    "turkce": "müstensih",
    "azerice1": "(yazmanı) köçürän",
    "azerice2": null,
    "azerice3": null,
    "azerice4": null,
    "baskurtca1": "küsirip yaⱬıvsı",
    "baskurtca2": null,
    "baskurtca3": null,
    "baskurtca4": null,
    "kazakca1": "köşirüvşi ",
    "kazakca2": "köşirmeşi",
    "kazakca3": null,
    "kazakca4": null,
    "kirgizca1": "köçürmöçü",
    "kirgizca2": null,
    "kirgizca3": null,
    "kirgizca4": null,
    "ozbekce1": "kàtib",
    "ozbekce2": null,
    "ozbekce3": null,
    "ozbekce4": null,
    "tatarca1": "küçirip yazuçı",
    "tatarca2": null,
    "tatarca3": null,
    "tatarca4": null,
    "turkmence1": "göçürici ",
    "turkmence2": "kǟtḯp",
    "turkmence3": null,
    "turkmence4": null,
    "uygurca1": "pütükçi ",
    "uygurca2": "köçürüp yazğuçi",
    "uygurca3": null,
    "uygurca4": null,
    "rusca1": "perepisçik",
    "rusca2": null,
    "rusca3": null,
    "rusca4": null
  }
]