[
  {
    "$kitaptaki_turkce": "müzākere",
    "lehce_id": "4528",
    "asil": "müzakere",
    "turkce": "müzakere",
    "azerice1": "müzãkirä",
    "azerice2": null,
    "azerice3": null,
    "azerice4": null,
    "baskurtca1": "käŋäşmä",
    "baskurtca2": null,
    "baskurtca3": null,
    "baskurtca4": null,
    "kazakca1": "talkılav",
    "kazakca2": null,
    "kazakca3": null,
    "kazakca4": null,
    "kirgizca1": "keŋeşme",
    "kirgizca2": null,
    "kirgizca3": null,
    "kirgizca4": null,
    "ozbekce1": "muzàkärä ",
    "ozbekce2": "mäslähätläşiş",
    "ozbekce3": null,
    "ozbekce4": null,
    "tatarca1": "kiŋäşmä",
    "tatarca2": null,
    "tatarca3": null,
    "tatarca4": null,
    "turkmence1": "maslahatlaşma",
    "turkmence2": null,
    "turkmence3": null,
    "turkmence4": null,
    "uygurca1": "muzakirä",
    "uygurca2": null,
    "uygurca3": null,
    "uygurca4": null,
    "rusca1": "delovaya beseda ",
    "rusca2": "soveşçaniye",
    "rusca3": null,
    "rusca4": null
  }
]