[
  {
    "$kitaptaki_turkce": "oturaklı",
    "lehce_id": "4752",
    "asil": "oturaklı",
    "turkce": "oturaklı",
    "azerice1": "sãbit",
    "azerice2": "ağır",
    "azerice3": null,
    "azerice4": null,
    "baskurtca1": "totoroklo",
    "baskurtca2": "nıklı",
    "baskurtca3": null,
    "baskurtca4": null,
    "kazakca1": "turaktı",
    "kazakca2": "salıkalı",
    "kazakca3": "salmaktı",
    "kazakca4": null,
    "kirgizca1": "bekem",
    "kirgizca2": "turuktū",
    "kirgizca3": null,
    "kirgizca4": null,
    "ozbekce1": "àğır",
    "ozbekce2": "väzmin",
    "ozbekce3": null,
    "ozbekce4": null,
    "tatarca1": "totırıklı",
    "tatarca2": "nıklı",
    "tatarca3": null,
    "tatarca4": null,
    "turkmence1": "salīkatlı",
    "turkmence2": "ağras",
    "turkmence3": null,
    "turkmence4": null,
    "uygurca1": "ciddi",
    "uygurca2": "salmaklik",
    "uygurca3": null,
    "uygurca4": null,
    "rusca1": "ustoyçivıy",
    "rusca2": "krepko (proçno) stoyaşçiy",
    "rusca3": null,
    "rusca4": null
  }
]