[
  {
    "$kitaptaki_turkce": "satıh",
    "lehce_id": "5360",
    "asil": "satıh",
    "turkce": "satıh",
    "azerice1": "säth",
    "azerice2": null,
    "azerice3": null,
    "azerice4": null,
    "baskurtca1": "ös ",
    "baskurtca2": "öst ",
    "baskurtca3": "yöⱬ",
    "baskurtca4": null,
    "kazakca1": "üst ",
    "kazakca2": "sırt ",
    "kazakca3": "bet",
    "kazakca4": null,
    "kirgizca1": "üstü ",
    "kirgizca2": "bet",
    "kirgizca3": null,
    "kirgizca4": null,
    "ozbekce1": "säth ",
    "ozbekce2": "üst ",
    "ozbekce3": "yüzä",
    "ozbekce4": null,
    "tatarca1": "ös ",
    "tatarca2": "öst ",
    "tatarca3": "yöz",
    "tatarca4": null,
    "turkmence1": "üst ",
    "turkmence2": "yüz",
    "turkmence3": null,
    "turkmence4": null,
    "uygurca1": "üst ",
    "uygurca2": "sirt ",
    "uygurca3": "bät",
    "uygurca4": null,
    "rusca1": "poverⱨnost'",
    "rusca2": null,
    "rusca3": null,
    "rusca4": null
  }
]