[
  {
    "$kitaptaki_turkce": "sebat",
    "lehce_id": "5394",
    "asil": "sebat",
    "turkce": "sebat",
    "azerice1": "säbat",
    "azerice2": null,
    "azerice3": null,
    "azerice4": null,
    "baskurtca1": "nıkışlık ",
    "baskurtca2": "nıkışmalık",
    "baskurtca3": null,
    "baskurtca4": null,
    "kazakca1": "ornıktılık ",
    "kazakca2": "turaktılık",
    "kazakca3": "tabandılık",
    "kazakca4": null,
    "kirgizca1": "turuktūluk",
    "kirgizca2": null,
    "kirgizca3": null,
    "kirgizca4": null,
    "ozbekce1": "sàbitlik ",
    "ozbekce2": "säbàt",
    "ozbekce3": null,
    "ozbekce4": null,
    "tatarca1": "nık toru",
    "tatarca2": null,
    "tatarca3": null,
    "tatarca4": null,
    "turkmence1": "tutanyerlilik",
    "turkmence2": null,
    "turkmence3": null,
    "turkmence4": null,
    "uygurca1": "dayimlık ",
    "uygurca2": "sabitlık",
    "uygurca3": null,
    "uygurca4": null,
    "rusca1": "postoyanstvo ",
    "rusca2": "nastoyçivost'",
    "rusca3": null,
    "rusca4": null
  }
]