[
  {
    "$kitaptaki_turkce": "serāzat",
    "lehce_id": "5455",
    "asil": "serazat",
    "turkce": "serazat",
    "azerice1": "azad",
    "azerice2": " hürr",
    "azerice3": null,
    "azerice4": null,
    "baskurtca1": "gämhiⱬ ",
    "baskurtca2": "moŋhoⱬ ",
    "baskurtca3": "vayımhıⱬ",
    "baskurtca4": null,
    "kazakca1": "jaybarakat ",
    "kazakca2": "beykam",
    "kazakca3": null,
    "kazakca4": null,
    "kirgizca1": "beyğam",
    "kirgizca2": null,
    "kirgizca3": null,
    "kirgizca4": null,
    "ozbekce1": "beğam ",
    "ozbekce2": "betäşviş",
    "ozbekce3": null,
    "ozbekce4": null,
    "tatarca1": "gamsız ",
    "tatarca2": "vayımsız",
    "tatarca3": null,
    "tatarca4": null,
    "turkmence1": "gayğısız ",
    "turkmence2": "gamsız",
    "turkmence3": null,
    "turkmence4": null,
    "uygurca1": "pärvasiz ",
    "uygurca2": "ğämsiz",
    "uygurca3": null,
    "uygurca4": null,
    "rusca1": "bespeçnıy ",
    "rusca2": "bezzabotnıy ",
    "rusca3": "vol'nıy",
    "rusca4": null
  }
]