[
  {
    "$kitaptaki_turkce": "seyrek",
    "lehce_id": "5506",
    "asil": "seyrek",
    "turkce": "seyrek",
    "azerice1": "seyräk",
    "azerice2": null,
    "azerice3": null,
    "azerice4": null,
    "baskurtca1": "hiräk ",
    "baskurtca2": "ⱨäl ",
    "baskurtca3": "osrak nämä",
    "baskurtca4": null,
    "kazakca1": "siyrek",
    "kazakca2": null,
    "kazakca3": null,
    "kazakca4": null,
    "kirgizca1": "seyrek",
    "kirgizca2": null,
    "kirgizca3": null,
    "kirgizca4": null,
    "ozbekce1": "siyräk",
    "ozbekce2": null,
    "ozbekce3": null,
    "ozbekce4": null,
    "tatarca1": "siräk ",
    "tatarca2": "ⱨäl ",
    "tatarca3": "oçrak närsä",
    "tatarca4": null,
    "turkmence1": "seyrek",
    "turkmence2": null,
    "turkmence3": null,
    "turkmence4": null,
    "uygurca1": "sirek ",
    "uygurca2": "şalaŋ",
    "uygurca3": null,
    "uygurca4": null,
    "rusca1": "redkiy",
    "rusca2": null,
    "rusca3": null,
    "rusca4": null
  }
]