[
  {
    "$kitaptaki_turkce": "silâhşor",
    "lehce_id": "5593",
    "asil": "silahşör",
    "turkce": "silahşör",
    "azerice1": "mähãrätli",
    "azerice2": "döyüşçi",
    "azerice3": null,
    "azerice4": null,
    "baskurtca1": "huğuşsı",
    "baskurtca2": null,
    "baskurtca3": null,
    "baskurtca4": null,
    "kazakca1": "javınger",
    "kazakca2": null,
    "kazakca3": null,
    "kazakca4": null,
    "kirgizca1": "mıktı asker",
    "kirgizca2": null,
    "kirgizca3": null,
    "kirgizca4": null,
    "ozbekce1": "mähàrätli cängci",
    "ozbekce2": null,
    "ozbekce3": null,
    "ozbekce4": null,
    "tatarca1": "suğışçı",
    "tatarca2": null,
    "tatarca3": null,
    "tatarca4": null,
    "turkmence1": "ökde söveşici",
    "turkmence2": null,
    "turkmence3": null,
    "turkmence4": null,
    "uygurca1": "kıliçvaz",
    "uygurca2": "cäŋçi",
    "uygurca3": null,
    "uygurca4": null,
    "rusca1": "umelıy boyets",
    "rusca2": null,
    "rusca3": null,
    "rusca4": null
  }
]