[
  {
    "$kitaptaki_turkce": "temsilci",
    "lehce_id": "6288",
    "asil": "temsilci",
    "turkce": "temsilci",
    "azerice1": "nümãyändä",
    "azerice2": "tämsilçi",
    "azerice3": null,
    "azerice4": null,
    "baskurtca1": "väkil",
    "baskurtca2": null,
    "baskurtca3": null,
    "baskurtca4": null,
    "kazakca1": "ökil",
    "kazakca2": null,
    "kazakca3": null,
    "kazakca4": null,
    "kirgizca1": "ökül",
    "kirgizca2": null,
    "kirgizca3": null,
    "kirgizca4": null,
    "ozbekce1": "väkil",
    "ozbekce2": null,
    "ozbekce3": null,
    "ozbekce4": null,
    "tatarca1": "väkil",
    "tatarca2": null,
    "tatarca3": null,
    "tatarca4": null,
    "turkmence1": "vekḯl",
    "turkmence2": null,
    "turkmence3": null,
    "turkmence4": null,
    "uygurca1": "väkil",
    "uygurca2": null,
    "uygurca3": null,
    "uygurca4": null,
    "rusca1": "predstavitel'",
    "rusca2": null,
    "rusca3": null,
    "rusca4": null
  }
]