{
  "$kitaptaki_turkce": "temsil (oyun)",
  "asil": "temsil (oyun)",
  "lehce_id": "6287",
  "turkce": "temsil",
  "azerice1": "tamaşa",
  "azerice2": null,
  "azerice3": null,
  "azerice4": null,
  "baskurtca1": "uyın",
  "baskurtca2": "tamaşa",
  "baskurtca3": null,
  "baskurtca4": null,
  "kazakca1": "spektakl'",
  "kazakca2": "oyın",
  "kazakca3": null,
  "kazakca4": null,
  "kirgizca1": "oyun",
  "kirgizca2": "spektakl",
  "kirgizca3": null,
  "kirgizca4": null,
  "ozbekce1": "spektakl",
  "ozbekce2": null,
  "ozbekce3": null,
  "ozbekce4": null,
  "tatarca1": "uyın",
  "tatarca2": "tamaşa",
  "tatarca3": null,
  "tatarca4": null,
  "turkmence1": "spektakl",
  "turkmence2": "oyun",
  "turkmence3": null,
  "turkmence4": null,
  "uygurca1": "oyun",
  "uygurca2": "spektakl",
  "uygurca3": null,
  "uygurca4": null,
  "rusca1": "spektakl'",
  "rusca2": null,
  "rusca3": null,
  "rusca4": null
}