[
  {
    "$kitaptaki_turkce": "teşbih",
    "lehce_id": "6350",
    "asil": "teşbih",
    "turkce": "teşbih",
    "azerice1": "täşbeh",
    "azerice2": null,
    "azerice3": null,
    "azerice4": null,
    "baskurtca1": "okşav",
    "baskurtca2": "tiŋläştiriv",
    "baskurtca3": null,
    "baskurtca4": null,
    "kazakca1": "uksasuv",
    "kazakca2": "uksav",
    "kazakca3": "tärizdenüv",
    "kazakca4": null,
    "kirgizca1": "okşoşū",
    "kirgizca2": null,
    "kirgizca3": null,
    "kirgizca4": null,
    "ozbekce1": "täşbeh",
    "ozbekce2": "oⱨşätiş",
    "ozbekce3": null,
    "ozbekce4": null,
    "tatarca1": "oⱨşau",
    "tatarca2": "tiŋläştirü",
    "tatarca3": null,
    "tatarca4": null,
    "turkmence1": "meŋzetme",
    "turkmence2": null,
    "turkmence3": null,
    "turkmence4": null,
    "uygurca1": "oⱨşitiş",
    "uygurca2": null,
    "uygurca3": null,
    "uygurca4": null,
    "rusca1": "upodobleniye",
    "rusca2": "sravneniye",
    "rusca3": "allegoriya",
    "rusca4": null
  }
]