[
  {
    "$kitaptaki_turkce": "utangaç",
    "lehce_id": "6642",
    "asil": "utangaç",
    "turkce": "utangaç",
    "azerice1": "utancag",
    "azerice2": null,
    "azerice3": null,
    "azerice4": null,
    "baskurtca1": "oyalsan ",
    "baskurtca2": "oyalıvsan",
    "baskurtca3": null,
    "baskurtca4": null,
    "kazakca1": "uyattı",
    "kazakca2": null,
    "kazakca3": null,
    "kazakca4": null,
    "kirgizca1": "uyattū",
    "kirgizca2": null,
    "kirgizca3": null,
    "kirgizca4": null,
    "ozbekce1": "uyätçän",
    "ozbekce2": null,
    "ozbekce3": null,
    "ozbekce4": null,
    "tatarca1": "oyalçan ",
    "tatarca2": "oyaluçan",
    "tatarca3": null,
    "tatarca4": null,
    "turkmence1": "utancaŋ",
    "turkmence2": "çekinceŋ",
    "turkmence3": null,
    "turkmence4": null,
    "uygurca1": "uyalçak",
    "uygurca2": " uyatçan",
    "uygurca3": null,
    "uygurca4": null,
    "rusca1": "stıdlivıy",
    "rusca2": null,
    "rusca3": null,
    "rusca4": null
  }
]