[
  {
    "$kitaptaki_turkce": "vakar",
    "lehce_id": "6756",
    "asil": "vakar",
    "turkce": "vakar",
    "azerice1": "tämkinlilik",
    "azerice2": null,
    "azerice3": null,
    "azerice4": null,
    "baskurtca1": "olpatlılık",
    "baskurtca2": "hakimlilik",
    "baskurtca3": "ölkärlik",
    "baskurtca4": null,
    "kazakca1": "salmaktılık",
    "kazakca2": "salıykalılık",
    "kazakca3": null,
    "kazakca4": null,
    "kirgizca1": "ōr-basırık",
    "kirgizca2": null,
    "kirgizca3": null,
    "kirgizca4": null,
    "ozbekce1": "vikàr ",
    "ozbekce2": "väzminlik",
    "ozbekce3": null,
    "ozbekce4": null,
    "tatarca1": "nıklık",
    "tatarca2": "töplilik",
    "tatarca3": " zurlık",
    "tatarca4": " tiränlik",
    "turkmence1": "ağraslık ",
    "turkmence2": "salikatlılık",
    "turkmence3": null,
    "turkmence4": null,
    "uygurca1": "salmaklik ",
    "uygurca2": null,
    "uygurca3": null,
    "uygurca4": null,
    "rusca1": "stepennost' ",
    "rusca2": "vajnost'",
    "rusca3": "solidnost'",
    "rusca4": null
  }
]