[
  {
    "$kitaptaki_turkce": "vestiyer",
    "lehce_id": "6837",
    "asil": "vestiyer",
    "turkce": "vestiyer",
    "azerice1": "garderob",
    "azerice2": null,
    "azerice3": null,
    "azerice4": null,
    "baskurtca1": "kiyim şkafı",
    "baskurtca2": null,
    "baskurtca3": null,
    "baskurtca4": null,
    "kazakca1": "kiyim ilgiş ",
    "kazakca2": "kiyimdik",
    "kazakca3": null,
    "kazakca4": null,
    "kirgizca1": "kiyim çeçṻçü cay",
    "kirgizca2": null,
    "kirgizca3": null,
    "kirgizca4": null,
    "ozbekce1": "garderob",
    "ozbekce2": null,
    "ozbekce3": null,
    "ozbekce4": null,
    "tatarca1": "kiyim şkafi",
    "tatarca2": null,
    "tatarca3": null,
    "tatarca4": null,
    "turkmence1": "garderob",
    "turkmence2": null,
    "turkmence3": null,
    "turkmence4": null,
    "uygurca1": "garderob",
    "uygurca2": null,
    "uygurca3": null,
    "uygurca4": null,
    "rusca1": "garderob",
    "rusca2": null,
    "rusca3": null,
    "rusca4": null
  }
]