[
  {
    "$kitaptaki_turkce": "vızıldamak",
    "lehce_id": "6848",
    "asil": "vızıldamak",
    "turkce": "vızıldamak",
    "azerice1": "sızlamag",
    "azerice2": null,
    "azerice3": null,
    "azerice4": null,
    "baskurtca1": "biⱬildäv ",
    "baskurtca2": "göjläv",
    "baskurtca3": null,
    "baskurtca4": null,
    "kazakca1": "ızıldav",
    "kazakca2": null,
    "kazakca3": null,
    "kazakca4": null,
    "kirgizca1": "bizildō",
    "kirgizca2": null,
    "kirgizca3": null,
    "kirgizca4": null,
    "ozbekce1": "vizillämàk",
    "ozbekce2": null,
    "ozbekce3": null,
    "ozbekce4": null,
    "tatarca1": "bizildäv ",
    "tatarca2": "göjläv",
    "tatarca3": null,
    "tatarca4": null,
    "turkmence1": "vızzıldamak",
    "turkmence2": null,
    "turkmence3": null,
    "turkmence4": null,
    "uygurca1": "vijildimak",
    "uygurca2": null,
    "uygurca3": null,
    "uygurca4": null,
    "rusca1": "juljat'",
    "rusca2": null,
    "rusca3": null,
    "rusca4": null
  }
]