[
  {
    "$kitaptaki_turkce": "yankı",
    "lehce_id": "6956",
    "asil": "yankı",
    "turkce": "yankı",
    "azerice1": "äks-säda",
    "azerice2": null,
    "azerice3": null,
    "azerice4": null,
    "baskurtca1": "yaŋrav ",
    "baskurtca2": "yaŋğırak",
    "baskurtca3": null,
    "baskurtca4": null,
    "kazakca1": "jaŋğırık",
    "kazakca2": null,
    "kazakca3": null,
    "kazakca4": null,
    "kirgizca1": "çaŋırık",
    "kirgizca2": null,
    "kirgizca3": null,
    "kirgizca4": null,
    "ozbekce1": "aks sädä",
    "ozbekce2": null,
    "ozbekce3": null,
    "ozbekce4": null,
    "tatarca1": "yaŋğırık",
    "tatarca2": "tavış yaŋğıravı",
    "tatarca3": null,
    "tatarca4": null,
    "turkmence1": "cübi oğrusı",
    "turkmence2": null,
    "turkmence3": null,
    "turkmence4": null,
    "uygurca1": "yançukçi",
    "uygurca2": null,
    "uygurca3": null,
    "uygurca4": null,
    "rusca1": "vor-karmannik",
    "rusca2": null,
    "rusca3": null,
    "rusca4": null
  }
]