[
  {
    "$kitaptaki_turkce": "zanāatkâr",
    "lehce_id": "7293",
    "asil": "zanaatkar",
    "turkce": "zanaatkar",
    "azerice1": "sänätkar",
    "azerice2": null,
    "azerice3": null,
    "azerice4": null,
    "baskurtca1": "osta",
    "baskurtca2": null,
    "baskurtca3": null,
    "baskurtca4": null,
    "kazakca1": "käsipker ",
    "kazakca2": "kolönerşi",
    "kazakca3": null,
    "kazakca4": null,
    "kirgizca1": "usta",
    "kirgizca2": null,
    "kirgizca3": null,
    "kirgizca4": null,
    "ozbekce1": "kàsib ",
    "ozbekce2": "hünärmänd",
    "ozbekce3": null,
    "ozbekce4": null,
    "tatarca1": "osta",
    "tatarca2": null,
    "tatarca3": null,
    "tatarca4": null,
    "turkmence1": "senetçi ",
    "turkmence2": "senetkǟr",
    "turkmence3": null,
    "turkmence4": null,
    "uygurca1": "hünävän ",
    "uygurca2": "usta",
    "uygurca3": null,
    "uygurca4": null,
    "rusca1": "remeslennik",
    "rusca2": null,
    "rusca3": null,
    "rusca4": null
  }
]