{
  "$kitaptaki_turkce": "zarf(mektup için) ",
  "asil": "zarf(mektup için) ",
  "lehce_id": "7304",
  "turkce": "zarf",
  "azerice1": "zärf",
  "azerice2": null,
  "azerice3": null,
  "azerice4": null,
  "baskurtca1": "konvert",
  "baskurtca2": null,
  "baskurtca3": null,
  "baskurtca4": null,
  "kazakca1": "konvert",
  "kazakca2": null,
  "kazakca3": null,
  "kazakca4": null,
  "kirgizca1": "konvert",
  "kirgizca2": null,
  "kirgizca3": null,
  "kirgizca4": null,
  "ozbekce1": "konvert",
  "ozbekce2": null,
  "ozbekce3": null,
  "ozbekce4": null,
  "tatarca1": "konvert",
  "tatarca2": null,
  "tatarca3": null,
  "tatarca4": null,
  "turkmence1": "bukca ",
  "turkmence2": "konvert",
  "turkmence3": null,
  "turkmence4": null,
  "uygurca1": "konvert ",
  "uygurca2": "lipapä",
  "uygurca3": null,
  "uygurca4": null,
  "rusca1": "konvert",
  "rusca2": null,
  "rusca3": null,
  "rusca4": null
}