[
  {
    "$kitaptaki_turkce": "ziyāfet",
    "lehce_id": "7374",
    "asil": "ziyafet",
    "turkce": "ziyafet",
    "azerice1": "ziyãfät",
    "azerice2": null,
    "azerice3": null,
    "azerice4": null,
    "baskurtca1": "banket",
    "baskurtca2": null,
    "baskurtca3": null,
    "baskurtca4": null,
    "kazakca1": "banket",
    "kazakca2": null,
    "kazakca3": null,
    "kazakca4": null,
    "kirgizca1": "zıyapat",
    "kirgizca2": null,
    "kirgizca3": null,
    "kirgizca4": null,
    "ozbekce1": "ziyàfät",
    "ozbekce2": null,
    "ozbekce3": null,
    "ozbekce4": null,
    "tatarca1": "banket",
    "tatarca2": null,
    "tatarca3": null,
    "tatarca4": null,
    "turkmence1": "zıyãpat ",
    "turkmence2": "oturılışık",
    "turkmence3": null,
    "turkmence4": null,
    "uygurca1": "ziyäpät",
    "uygurca2": null,
    "uygurca3": null,
    "uygurca4": null,
    "rusca1": "banket",
    "rusca2": null,
    "rusca3": null,
    "rusca4": null
  }
]