[
  {
    "$kitaptaki_turkce": "zorlamak",
    "lehce_id": "7383",
    "asil": "zorlamak",
    "turkce": "zorlamak",
    "azerice1": "zorlamag",
    "azerice2": null,
    "azerice3": null,
    "azerice4": null,
    "baskurtca1": "mäjbür itiv ",
    "baskurtca2": "kösläv",
    "baskurtca3": null,
    "baskurtca4": null,
    "kazakca1": "zorlav",
    "kazakca2": null,
    "kazakca3": null,
    "kazakca4": null,
    "kirgizca1": "zorduktō",
    "kirgizca2": null,
    "kirgizca3": null,
    "kirgizca4": null,
    "ozbekce1": "zorlämàḳ ",
    "ozbekce2": "macbür ḳılmàḳ",
    "ozbekce3": null,
    "ozbekce4": null,
    "tatarca1": "mäcbür itü ",
    "tatarca2": "kösläv",
    "tatarca3": null,
    "tatarca4": null,
    "turkmence1": "zōrlamak ",
    "turkmence2": "mecbūr etmek",
    "turkmence3": null,
    "turkmence4": null,
    "uygurca1": "zorlimak",
    "uygurca2": null,
    "uygurca3": null,
    "uygurca4": null,
    "rusca1": "prinujdat'",
    "rusca2": "zastavl'at'",
    "rusca3": null,
    "rusca4": null
  }
]