[
  {
    "$kitaptaki_turkce": "zırva",
    "lehce_id": "7352",
    "asil": "zırva",
    "turkce": "zırva",
    "azerice1": "boşboğazlıg ",
    "azerice2": "cäfängiyat ",
    "azerice3": "boş söylämäk",
    "azerice4": null,
    "baskurtca1": "buş hüⱬ",
    "baskurtca2": null,
    "baskurtca3": null,
    "baskurtca4": null,
    "kazakca1": "bos söz",
    "kazakca2": null,
    "kazakca3": null,
    "kazakca4": null,
    "kirgizca1": "tantık söz",
    "kirgizca2": null,
    "kirgizca3": null,
    "kirgizca4": null,
    "ozbekce1": "bekàrçi gäp ",
    "ozbekce2": "behüdä gäp ",
    "ozbekce3": "säfsätä",
    "ozbekce4": null,
    "tatarca1": "buş süz",
    "tatarca2": null,
    "tatarca3": null,
    "tatarca4": null,
    "turkmence1": "boş söz ",
    "turkmence2": "samahallı",
    "turkmence3": null,
    "turkmence4": null,
    "uygurca1": "boş söz",
    "uygurca2": null,
    "uygurca3": null,
    "uygurca4": null,
    "rusca1": "pustıye razgovorı ",
    "rusca2": "boltovn'a",
    "rusca3": null,
    "rusca4": null
  }
]