[
  {
    "$kitaptaki_turkce": "çirkef",
    "lehce_id": "968",
    "asil": "çirkef",
    "turkce": "çirkef",
    "azerice1": "çirkâb",
    "azerice2": null,
    "azerice3": null,
    "azerice4": null,
    "baskurtca1": "bısrak",
    "baskurtca2": "şamtır",
    "baskurtca3": "şalkı",
    "baskurtca4": null,
    "kazakca1": "bıksık",
    "kazakca2": "pasık",
    "kazakca3": null,
    "kazakca4": null,
    "kirgizca1": "akır-çikir",
    "kirgizca2": null,
    "kirgizca3": null,
    "kirgizca4": null,
    "ozbekce1": "iflàslik",
    "ozbekce2": "isḳırtlik",
    "ozbekce3": null,
    "ozbekce4": null,
    "tatarca1": "şapşak",
    "tatarca2": "şakşı",
    "tatarca3": "pıçrak",
    "tatarca4": null,
    "turkmence1": "hapa",
    "turkmence2": "çirk",
    "turkmence3": null,
    "turkmence4": null,
    "uygurca1": "näcis",
    "uygurca2": "jirkänç",
    "uygurca3": null,
    "uygurca4": null,
    "rusca1": "gr'az'",
    "rusca2": "neçistótı",
    "rusca3": null,
    "rusca4": null
  }
]