[
  {
    "$kitaptaki_turkce": "üstü (para için)",
    "lehce_id": "6720",
    "asil": "üstü (para için)",
    "turkce": "para üstü",
    "azerice1": "pulun artığını (vermä)",
    "azerice2": null,
    "azerice3": null,
    "azerice4": null,
    "baskurtca1": "kaytarıp birilgän aksa",
    "baskurtca2": null,
    "baskurtca3": null,
    "baskurtca4": null,
    "kazakca1": "kayıruv (akşa üşin)",
    "kazakca2": null,
    "kazakca3": null,
    "kazakca4": null,
    "kirgizca1": "kaytanm akça",
    "kirgizca2": null,
    "kirgizca3": null,
    "kirgizca4": null,
    "ozbekce1": "kaytım",
    "ozbekce2": null,
    "ozbekce3": null,
    "ozbekce4": null,
    "tatarca1": "kaytarıp birilgän akça",
    "tatarca2": null,
    "tatarca3": null,
    "tatarca4": null,
    "turkmence1": "gaytarğı",
    "turkmence2": null,
    "turkmence3": null,
    "turkmence4": null,
    "uygurca1": "närⱨ ",
    "uygurca2": "üsti",
    "uygurca3": null,
    "uygurca4": null,
    "rusca1": "sdaça",
    "rusca2": null,
    "rusca3": null,
    "rusca4": null
  }
]