[
  {
    "$kitaptaki_turkce": "şahsī",
    "lehce_id": "5813",
    "asil": "şahsi",
    "turkce": "şahsi",
    "azerice1": "şäⱨsi",
    "azerice2": null,
    "azerice3": null,
    "azerice4": null,
    "baskurtca1": "şäⱨsi",
    "baskurtca2": null,
    "baskurtca3": null,
    "baskurtca4": null,
    "kazakca1": "menşikti",
    "kazakca2": null,
    "kazakca3": null,
    "kazakca4": null,
    "kirgizca1": "ceke",
    "kirgizca2": "özdük",
    "kirgizca3": null,
    "kirgizca4": null,
    "ozbekce1": "şaⱨsiy",
    "ozbekce2": null,
    "ozbekce3": null,
    "ozbekce4": null,
    "tatarca1": "şäⱨsi",
    "tatarca2": null,
    "tatarca3": null,
    "tatarca4": null,
    "turkmence1": "şahsı",
    "turkmence2": null,
    "turkmence3": null,
    "turkmence4": null,
    "uygurca1": "şäⱨsiy",
    "uygurca2": null,
    "uygurca3": null,
    "uygurca4": null,
    "rusca1": "liçnıy",
    "rusca2": "personal'nıy",
    "rusca3": null,
    "rusca4": null
  }
]